[
  {
    "id": 1773082340431,
    "url": "https://labs.google/fl...​",
    "title": "Video",
    "status": "OK",
    "error": null,
    "created_at": "2026-03-09T18:52:20.431Z"
  },
  {
    "id": 1773080981791,
    "url": "https://youtu.be/V1rbZoyL0oQ?si=tsATv5H55bS-ioxJ",
    "title": "Video",
    "status": "OK",
    "error": null,
    "created_at": "2026-03-09T18:29:41.791Z"
  },
  {
    "id": 1773080922108,
    "url": "https://vt.tiktok.com/ZSuM84oe2/",
    "title": "Video",
    "status": "OK",
    "error": null,
    "created_at": "2026-03-09T18:28:42.108Z"
  },
  {
    "id": 1773026749873,
    "url": "https://youtu.be/kknKs7cAcO8?si=M49E0alttSl7LP5X",
    "title": "Video",
    "status": "OK",
    "error": null,
    "created_at": "2026-03-09T03:25:49.873Z"
  },
  {
    "id": 1773026462028,
    "url": "https://youtu.be/wANgVxMPePs?si=5vNEUM7wf_xdlQoC",
    "title": "Video",
    "status": "OK",
    "error": null,
    "created_at": "2026-03-09T03:21:02.028Z"
  },
  {
    "id": 1773026239204,
    "url": "https://vt.tiktok.com/ZSujSQWVb/",
    "title": "Video",
    "status": "OK",
    "error": null,
    "created_at": "2026-03-09T03:17:19.204Z"
  },
  {
    "id": 1773026198759,
    "url": "https://youtu.be/wANgVxMPePs?si=5vNEUM7wf_xdlQoC",
    "title": "Video",
    "status": "OK",
    "error": null,
    "created_at": "2026-03-09T03:16:38.759Z"
  },
  {
    "id": 1773026170393,
    "url": "https://youtu.be/K17df81RL9Y?si=FUdEfzfOv-xIc2O7",
    "title": "Video",
    "status": "OK",
    "error": null,
    "created_at": "2026-03-09T03:16:10.393Z"
  },
  {
    "id": 1773025990284,
    "url": "https://youtu.be/K17df81RL9Y?si=FUdEfzfOv-xIc2O7",
    "title": "Error",
    "status": "DownloadFailed",
    "error": null,
    "created_at": "2026-03-09T03:13:10.284Z"
  },
  {
    "id": 1773025638612,
    "url": "https://youtu.be/wANgVxMPePs?si=5vNEUM7wf_xdlQoC",
    "title": "After Dark x Sweater Weather (ULTRA Slowed and Reverb)",
    "status": "OK",
    "error": null,
    "created_at": "2026-03-09T03:07:18.612Z"
  },
  {
    "id": 1773025611473,
    "url": "https://youtu.be/K17df81RL9Y?si=FUdEfzfOv-xIc2O7",
    "title": "AURORA - Cure For Me",
    "status": "OK",
    "error": null,
    "created_at": "2026-03-09T03:06:51.473Z"
  },
  {
    "id": 1773025591618,
    "url": "https://youtu.be/K17df81RL9Y?si=FUdEfzfOv-xIc2O7",
    "title": "AURORA - Cure For Me",
    "status": "OK",
    "error": null,
    "created_at": "2026-03-09T03:06:31.618Z"
  },
  {
    "id": 1773025551980,
    "url": "https://youtu.be/wANgVxMPePs?si=5vNEUM7wf_xdlQoC",
    "title": "After Dark x Sweater Weather (ULTRA Slowed and Reverb)",
    "status": "OK",
    "error": null,
    "created_at": "2026-03-09T03:05:51.980Z"
  },
  {
    "id": 1773025344617,
    "url": "https://youtu.be/K17df81RL9Y?si=FUdEfzfOv-xIc2O7",
    "title": "AURORA - Cure For Me",
    "status": "OK",
    "error": null,
    "created_at": "2026-03-09T03:02:24.617Z"
  }
]